[
    {
        "title": "Indumentaria",
        "icon": "{GiClothes}",
        "Childrens":
        [
            {
                "title": "Remeras",
                "icon": "{FaTshirt}",
                "path": "/"
            },
            {
                "title": "Chombas",
                "icon": "{GiShirt}",
                "path": "/"
            },
            {
                "title": "Chombas",
                "icon": "{GiShirt}",
                "path": "/"
            },
            {
                "title": "Buzos",
                "icon": "{GiPoloShirt}",
                "path": "/"
            },
            {
                "title": "Pantalones",
                "icon": "{GiArmoredPants}",
                "path": "/"
            }
        ]
    },
    {
        "title": "Cascos",
        "icon": "{GiFullMotorcycleHelmet}",
        "Childrens":
        [
            {
                "title": "Honda",
                "icon": "/",
                "path": "/"
            },
            {
                "title": "Yamaha",
                "icon": "/",
                "path": "/"
            },
            {
                "title": "Kawasaki",
                "icon": "/",
                "path": "/"
            },
            {
                "title": "BMW",
                "icon": "/",
                "path": "/"
            },            
            {
                "title": "Mercedes Benz",
                "icon": "/",
                "path": "/"
            }
        ]
    }   
]